iotio/Client.py
iotio/Device.py
iotio/DeviceType.py
iotio/Endpoint.py
iotio/EndpointResource.py
iotio/Errors.py
iotio/IoTClient.py
iotio/IoTManager.py
iotio/Manager.py
iotio/PacketEncoder.py
iotio/__init__.py
iotio/__main__.py
iotio/error.py
iotio/exceptions.py
iotio/types.py
iot.io-0.4.10.dist-info/LICENSE.md
iot.io-0.4.10.dist-info/METADATA
iot.io-0.4.10.dist-info/WHEEL
iot.io-0.4.10.dist-info/top_level.txt
iot.io-0.4.10.dist-info/RECORD
