Metadata-Version: 2.1
Name: iot.io
Version: 0.4.10
Summary: A management API for connecting and managing Clients via websocket connections.
Home-page: https://github.com/dylancrockett/iot.io
Author: Dylan Crockett
Author-email: dylanrcrockett@gmail.com
License: MIT
Project-URL: Documentation, https://iotio.readthedocs.io/
Project-URL: Source Code, https://github.com/dylancrockett/iot.io
Platform: UNKNOWN
Classifier: Programming Language :: Python :: 3
Classifier: License :: OSI Approved :: MIT License
Classifier: Operating System :: OS Independent
Requires-Python: >=3.7
Requires-Dist: gevent
Requires-Dist: gevent-websocket
Requires-Dist: flask
Requires-Dist: flask-sockets
